{
    "os": "macOS-10.16-x86_64-i386-64bit",
    "python": "3.8.8",
    "heartbeatAt": "2021-11-27T02:35:33.460220",
    "startedAt": "2021-11-27T02:35:26.896156",
    "docker": null,
    "cpu_count": 4,
    "cuda": null,
    "args": [
        "-c",
        "configs/one_batch.json"
    ],
    "state": "running",
    "program": "/Users/khaykingleb/Dropbox/Text-to-Speech/main.py",
    "codePath": "main.py",
    "git": {
        "remote": "git@github.com:khaykingleb/Text-to-Speech.git",
        "commit": "8d174729a58ec80924c66c572a72670ca51c6015"
    },
    "email": "khaykingleb@gmail.com",
    "root": "/Users/khaykingleb/Dropbox/Text-to-Speech",
    "host": "Glebs-MacBook-Pro-2.local",
    "username": "khaykingleb",
    "executable": "/opt/anaconda3/bin/python"
}
